wtf_calculator/__init__.py
wtf_calculator-0.2.3.dist-info/LICENSE
wtf_calculator-0.2.3.dist-info/METADATA
wtf_calculator-0.2.3.dist-info/WHEEL
wtf_calculator-0.2.3.dist-info/top_level.txt
wtf_calculator-0.2.3.dist-info/RECORD
